Metadata-Version: 2.4
Name: simple-snowflake-mcp
Version: 0.2.0
Summary: Simple Snowflake MCP Server to work behind a corporate proxy
Author-email: Yann Barraud <yann@barraud.io>
License: MIT License
License-File: LICENSE
Keywords: mcp,proxy,server,snowflake
Classifier: License :: OSI Approved :: MIT License
Classifier: Operating System :: OS Independent
Classifier: Programming Language :: Python :: 3
Requires-Python: >=3.10
Requires-Dist: mcp>=1.10.1
Requires-Dist: pydantic
Requires-Dist: python-dotenv
Requires-Dist: pyyaml
Requires-Dist: snowflake-connector-python
